html5tidy
html5tidy.py
setup.py
html5tidy.egg-info/PKG-INFO
html5tidy.egg-info/SOURCES.txt
html5tidy.egg-info/dependency_links.txt
html5tidy.egg-info/requires.txt
html5tidy.egg-info/top_level.txt