Metadata-Version: 1.1
Name: html5tidy
Version: 1.0
Summary: Simple wrapper around html5lib & lxml.etree to "tidy" html in the wild to well-formed xml/html
Home-page: http://automatist.org/
Author: Michael Murtaugh
Author-email: mm@automatist.org
License: UNKNOWN
Platform: UNKNOWN
Classifier: Development Status :: 4 - Beta
Classifier: Operating System :: OS Independent
Classifier: Environment :: Other Environment
Classifier: Environment :: Web Environment
Classifier: Intended Audience :: Developers
Classifier: License :: OSI Approved :: GNU General Public License v3 or later (GPLv3+)
Classifier: Natural Language :: English
Classifier: Programming Language :: Python
Classifier: Topic :: Text Processing :: Markup :: HTML
Classifier: Topic :: Text Processing :: Filters
Classifier: Topic :: Utilities
